plone/releaser/__init__.py
plone/releaser/base.py
plone/releaser/buildout.py
plone/releaser/changelog.py
plone/releaser/db.py
plone/releaser/manage.py
plone/releaser/package.py
plone/releaser/pip.py
plone/releaser/pypi.py
plone/releaser/release.py
plone/releaser/utils.py
plone/releaser/tests/__init__.py
plone/releaser/tests/test_buildout.py
plone/releaser/tests/test_buildout2pip.py
plone/releaser/tests/test_changelog.py
plone/releaser/tests/test_constraints2versions.py
plone/releaser/tests/test_mxdev_checkouts.py
plone/releaser/tests/test_mxdev_sources.py
plone/releaser/tests/test_pip.py
plone/releaser/tests/test_source.py
plone/releaser/tests/test_utils.py
plone/releaser/tests/test_versions2constraints.py
plone/releaser/tests/input/changes.md
plone/releaser/tests/input/changes.rst
plone/releaser/tests/input/checkouts.cfg
plone/releaser/tests/input/constraints.txt
plone/releaser/tests/input/constraints2.txt
plone/releaser/tests/input/constraints3.txt
plone/releaser/tests/input/constraints4.txt
plone/releaser/tests/input/mxcheckouts.ini
plone/releaser/tests/input/mxsources.ini
plone/releaser/tests/input/sources.cfg
plone/releaser/tests/input/versions.cfg
plone/releaser/tests/input/versions2.cfg
plone/releaser/tests/input/versions3.cfg
plone/releaser/tests/input/versions4.cfg
plone_releaser-3.0.0.dist-info/METADATA
plone_releaser-3.0.0.dist-info/WHEEL
plone_releaser-3.0.0.dist-info/entry_points.txt
plone_releaser-3.0.0.dist-info/top_level.txt
plone_releaser-3.0.0.dist-info/RECORD
