Metadata-Version: 2.4
Name: plone.releaser
Version: 3.0.0
Summary: Plone release management utilities
Home-page: https://github.com/plone/plone.releaser
Author: Eric Steele
Author-email: eric@esteele.net
License: GPL
Keywords: plone release
Classifier: Development Status :: 5 - Production/Stable
Classifier: Framework :: Plone
Classifier: Framework :: Plone :: 6.2
Classifier: License :: OSI Approved :: GNU General Public License (GPL)
Classifier: Programming Language :: Python
Classifier: Programming Language :: Python :: 3.10
Classifier: Programming Language :: Python :: 3.11
Requires-Python: >=3.10
Requires-Dist: argh
Requires-Dist: gitpython>=3.0.0
Requires-Dist: configparser
Requires-Dist: packaging
Requires-Dist: progress
Requires-Dist: zest.releaser[recommended]>=7.2.0
Requires-Dist: zestreleaser.towncrier>=1.3.0
Requires-Dist: docutils
Provides-Extra: test
Requires-Dist: pytest; extra == "test"
Dynamic: author
Dynamic: author-email
Dynamic: classifier
Dynamic: description
Dynamic: description-content-type
Dynamic: home-page
Dynamic: keywords
Dynamic: license
Dynamic: provides-extra
Dynamic: requires-dist
Dynamic: requires-python
Dynamic: summary
